kryptoxin/__init__.py
kryptoxin/__main__.py
kryptoxin/__version__.py
kryptoxin/core/__init__.py
kryptoxin/core/cli.py
kryptoxin/core/constants.py
kryptoxin/core/conv.py
kryptoxin/core/log.py
kryptoxin/core/toxin.py
kryptoxin/crypto/__init__.py
kryptoxin/crypto/aes.py
kryptoxin/crypto/base64.py
kryptoxin/crypto/caesar.py
kryptoxin/crypto/pbkdf2.py
kryptoxin/crypto/random.py
kryptoxin/output/__init__.py
kryptoxin/output/csharp.py
kryptoxin/output/powershell.py
kryptoxin/output/unformatted.py
kryptoxin/output/vba.py
kryptoxin/templates/csharp/actions/custom.jinja
kryptoxin/templates/csharp/actions/load-library.jinja
kryptoxin/templates/csharp/actions/print.jinja
kryptoxin/templates/csharp/decrypt/aes-dotnet.jinja
kryptoxin/templates/csharp/transform/hexstr2bytearray.jinja
kryptoxin/templates/powershell/actions/custom.jinja
kryptoxin/templates/powershell/actions/load-asm.jinja
kryptoxin/templates/powershell/actions/print.jinja
kryptoxin/templates/powershell/decode/base64.jinja
kryptoxin/templates/powershell/decrypt/aes-dotnet.jinja
kryptoxin/templates/vba/actions/load-asm.jinja
kryptoxin/templates/vba/decrypt/aes-dotnet.jinja
kryptoxin/templates/vba/decrypt/caesar-native.jinja
kryptoxin/templates/vba/transform/bytearraytostring.jinja
kryptoxin-0.9.9.dist-info/LICENSE
kryptoxin-0.9.9.dist-info/METADATA
kryptoxin-0.9.9.dist-info/WHEEL
kryptoxin-0.9.9.dist-info/top_level.txt
kryptoxin-0.9.9.dist-info/zip-safe
kryptoxin-0.9.9.dist-info/RECORD
