Metadata-Version: 2.1
Name: kryptoxin
Version: 0.9.9
Summary: A security-oriented payload encryption tool written in Python.
Home-page: https://github.com/e3prom/kryptoxin
Author: Nicolas Chabbey
Author-email: eprom@toor.si
License: GNU Affero General Public License v3
Keywords: security,encryption
Classifier: Programming Language :: Python :: 3
Classifier: License :: OSI Approved :: GNU Affero General Public License v3
Classifier: Operating System :: OS Independent
Classifier: Topic :: Security
Classifier: Topic :: Security :: Cryptography
Classifier: Intended Audience :: End Users/Desktop
Requires-Python: >=3.7
License-File: LICENSE
Requires-Dist: pycryptodome
Requires-Dist: click
Requires-Dist: Jinja2
